miffi/__init__.py
miffi/bibtex.py
miffi/constants.py
miffi/miffi_logo.png
miffi/protocols.conf
miffi/protocols/__init__.py
miffi/protocols/protocol_miffi.py
miffi/tests/__init__.py
miffi/tests/test_protocols_miffi.py
miffi/viewers/__init__.py
miffi/viewers/viewer.py
miffi/wizards/__init__.py
miffi/wizards/wizard_miffi.py
scipion_em_miffi-1.1.0.dist-info/LICENSE
scipion_em_miffi-1.1.0.dist-info/METADATA
scipion_em_miffi-1.1.0.dist-info/WHEEL
scipion_em_miffi-1.1.0.dist-info/entry_points.txt
scipion_em_miffi-1.1.0.dist-info/top_level.txt
scipion_em_miffi-1.1.0.dist-info/RECORD
