Metadata-Version: 2.1
Name: scipion-em-miffi
Version: 1.1.0
Summary: Plugin to use miffi within the Scipion framework
Author-email: Scipion Team <scipion@cnb.csic.es>
License: GNU General Public License v3 (GPLv3)
Project-URL: Homepage, https://github.com/scipion-em/scipion-em-miffi
Project-URL: Repository, https://github.com/scipion-em/scipion-em-miffi
Project-URL: Issues, https://github.com/scipion-em/scipion-em-miffi/issues
Keywords: scipion,cryoem,spa,imageprocessing,scipion-3.0
Classifier: Development Status :: 5 - Production/Stable
Classifier: License :: OSI Approved :: GNU General Public License v3 (GPLv3)
Classifier: Programming Language :: Python :: 3
Requires-Python: >=3.8
License-File: LICENSE
